hprmat/hprmat.py
hprmat/hprmat_fortran.cpython-314-darwin.so
hprmat/test_ex1.py
hprmat-1.0.0.dist-info/METADATA
hprmat-1.0.0.dist-info/WHEEL
hprmat-1.0.0.dist-info/top_level.txt
hprmat-1.0.0.dist-info/RECORD
