Metadata-Version: 2.4
Name: hprmat
Version: 1.0.0
Summary: High-Performance R-Matrix Solver for Nuclear Physics
Author: Jin Lei
License: MIT
Project-URL: Homepage, https://github.com/jinlei/hprmat
Project-URL: Documentation, https://github.com/jinlei/hprmat#readme
Project-URL: Repository, https://github.com/jinlei/hprmat
Project-URL: Issues, https://github.com/jinlei/hprmat/issues
Keywords: nuclear physics,R-matrix,scattering,coupled-channel,LAPACK,GPU,cuSOLVER,Fortran
Classifier: Development Status :: 4 - Beta
Classifier: Intended Audience :: Science/Research
Classifier: Topic :: Scientific/Engineering :: Physics
Classifier: License :: OSI Approved :: MIT License
Classifier: Programming Language :: Python :: 3
Classifier: Programming Language :: Python :: 3.9
Classifier: Programming Language :: Python :: 3.10
Classifier: Programming Language :: Python :: 3.11
Classifier: Programming Language :: Python :: 3.12
Classifier: Programming Language :: Python :: 3.13
Classifier: Programming Language :: Fortran
Classifier: Operating System :: POSIX :: Linux
Classifier: Operating System :: MacOS
Requires-Python: >=3.9
Requires-Dist: numpy>=1.20
Provides-Extra: dev
Requires-Dist: pytest>=7.0; extra == "dev"
Requires-Dist: pytest-cov; extra == "dev"
